MANIFEST.in
README.md
setup.py
examples/__init__.py
examples/change_servo_id.py
examples/control_servo_traj_1.py
examples/control_servo_traj_2.py
examples/control_servo_traj_3.py
examples/read_any_param.py
examples/read_any_param_cache.py
examples/read_errors_and_servo_information.py
examples/read_servo_max_velocity.py
examples/read_servo_motion_queue.py
examples/read_servo_nmt_state.py
examples/read_servo_trajectory_time.py
rdrive/Makefile
rdrive/__init__.py
rdrive/core.mk
rdrive/version
rdrive.egg-info/PKG-INFO
rdrive.egg-info/SOURCES.txt
rdrive.egg-info/dependency_links.txt
rdrive.egg-info/not-zip-safe
rdrive.egg-info/requires.txt
rdrive.egg-info/top_level.txt
rdrive/include/api.h
rdrive/lib/libservo_api-32bit.dll
rdrive/lib/libservo_api-64bit.dll
rdrive/servo/__init__.py
rdrive/servo/api.py
rdrive/servo/constants.py
rdrive/src/api.c
rdrive/src/co_common.c
rdrive/src/co_common.h
rdrive/src/crc16-ccitt.c
rdrive/src/crc16-ccitt.h
rdrive/src/logging.c
rdrive/src/logging.h
rdrive/src/rb_tools.c
rdrive/src/rb_tools.h
rdrive/src/usbcan_config.h
rdrive/src/usbcan_proto.c
rdrive/src/usbcan_proto.h
rdrive/src/usbcan_types.c
rdrive/src/usbcan_types.h
rdrive/src/usbcan_util.c
rdrive/src/usbcan_util.h