Metadata-Version: 2.1
Name: rdrive
Version: 1.0.40
Summary: Python API for RDrive servomotors
Home-page: https://rozum.com
Author: Rozum Robotics
Author-email: dev@rozum.com
License: Apache License 2.0
Platform: UNKNOWN
Classifier: License :: OSI Approved :: Apache Software License
Classifier: Development Status :: 5 - Production/Stable
Classifier: Programming Language :: Python
Classifier: Programming Language :: Python :: 3
Classifier: Programming Language :: Python :: Implementation :: CPython
Classifier: Operating System :: MacOS
Classifier: Operating System :: Microsoft :: Windows
Classifier: Operating System :: POSIX :: Linux
